setup.py
ppty/__init__.py
ppty/__main__.py
ppty/utils.py
ppty.egg-info/PKG-INFO
ppty.egg-info/SOURCES.txt
ppty.egg-info/dependency_links.txt
ppty.egg-info/entry_points.txt
ppty.egg-info/top_level.txt