Metadata-Version: 1.0
Name: ppty
Version: 0.1.0
Summary: Run process in pseudoterminal
Home-page: https://github.com/qingyunha/ppty
Author: Tao Qingyun
Author-email: 84576765@qq.com
License: UNKNOWN
Keywords: pty terminal
Platform: UNKNOWN
